django_model_map/__init__.py
django_model_map/apps.py
django_model_map/management/__init__.py
django_model_map/management/commands/__init__.py
django_model_map/management/commands/modelmap.py
django_model_map-0.2.0.dist-info/licenses/LICENSE
django_model_map-0.2.0.dist-info/METADATA
django_model_map-0.2.0.dist-info/WHEEL
django_model_map-0.2.0.dist-info/top_level.txt
django_model_map-0.2.0.dist-info/RECORD
