Metadata-Version: 2.4
Name: django-model-map
Version: 0.2.0
Summary: A CLI tool to map Django model relationships for optimizing queries (select_related vs prefetch_related).
Home-page: https://github.com/swayll/django-model-map/
Author: Nikolay Fedorov
Author-email: 40500428+swayll@users.noreply.github.com
License: MIT
Classifier: Environment :: Web Environment
Classifier: Framework :: Django
Classifier: Intended Audience :: Developers
Classifier: License :: OSI Approved :: MIT License
Classifier: Operating System :: OS Independent
Classifier: Programming Language :: Python :: 3
Classifier: Programming Language :: Python :: 3.8
Classifier: Programming Language :: Python :: 3.9
Classifier: Programming Language :: Python :: 3.10
Classifier: Programming Language :: Python :: 3.11
Classifier: Programming Language :: Python :: 3.12
Classifier: Programming Language :: Python :: 3.13
Requires-Python: >=3.8
License-File: LICENSE
Requires-Dist: Django>=3.2
Dynamic: license-file
